AmaSalesEstimator.py
AmaSalesEstimator-1.0.3.dist-info/LICENSE
AmaSalesEstimator-1.0.3.dist-info/METADATA
AmaSalesEstimator-1.0.3.dist-info/WHEEL
AmaSalesEstimator-1.0.3.dist-info/top_level.txt
AmaSalesEstimator-1.0.3.dist-info/RECORD
