Metadata-Version: 2.1
Name: AmaSalesEstimator
Version: 1.0.3
Summary: 亚马逊预计销量计算器
Home-page: https://gitee.com/joeyoung18/AmaSalesEstiamtor
Author: JoeYoung
Author-email: 1022104172@qq.com
License: MIT Licence
Keywords: amazon,sales
Platform: any
License-File: LICENSE
